setup.py
django_openportfolio.egg-info/PKG-INFO
django_openportfolio.egg-info/SOURCES.txt
django_openportfolio.egg-info/dependency_links.txt
django_openportfolio.egg-info/not-zip-safe
django_openportfolio.egg-info/requires.txt
django_openportfolio.egg-info/top_level.txt
openportfolioapp/__init__.py
openportfolioapp/admin.py
openportfolioapp/urls.py
openportfolioapp/management/__init__.py
openportfolioapp/management/commands/__init__.py
openportfolioapp/management/commands/fetch-prices.py
openportfolioapp/management/commands/import-trades.py
openportfolioapp/management/commands/openportfolio-daily.py
openportfolioapp/migrations/0001_initial.py
openportfolioapp/migrations/__init__.py
openportfolioapp/models/__init__.py
openportfolioapp/models/assetclass.py
openportfolioapp/models/company.py
openportfolioapp/models/currency.py
openportfolioapp/models/gicssector.py
openportfolioapp/models/interestrate.py
openportfolioapp/models/investment.py
openportfolioapp/models/portfolio.py
openportfolioapp/models/price.py
openportfolioapp/models/subclassing.py
openportfolioapp/models/trade.py
openportfolioapp/models/tradeallocation.py
openportfolioapp/models/datafiles/__init__.py
openportfolioapp/models/datafiles/datadefinition.py
openportfolioapp/models/datafiles/tradedatafile.py
openportfolioapp/models/investments/__init__.py
openportfolioapp/models/investments/listedequity.py
openportfolioapp/models/investments/savingsaccount.py
openportfolioapp/models/prices/__init__.py
openportfolioapp/models/prices/currencyprice.py
openportfolioapp/models/prices/investmentprice.py
openportfolioapp/models/prices/listedequityprice.py
openportfolioapp/models/prices/savingsaccountprice.py
openportfolioapp/templatetags/__init__.py
openportfolioapp/templatetags/openportfolioapp_extras.py
openportfolioapp/templatetags/pyformat.py
openportfolioapp/utils/__init__.py
openportfolioapp/utils/currencyhistory.py
openportfolioapp/utils/ofx.py
openportfolioapp/utils/update_helpers.py
openportfolioapp/utils/utils.py
openportfolioapp/views/__init__.py
openportfolioapp/views/admin.py
openportfolioapp/views/investment.py
openportfolioapp/views/portfolio.py