Metadata-Version: 1.0
Name: django-openportfolio
Version: 0.1.0
Summary: 
